{
  "sailnumber": "CAN/CAN7779",
  "country": "CAN",
  "name": "Mach 2",
  "rating": {
    "gph": 391.0,
    "osn": 382.4,
    "triple_offshore": [
      1.3432,
      1.7225,
      1.9991
    ],
    "triple_inshore": [
      1.0244,
      1.3733,
      1.6374
    ]
  },
  "boat": {
    "builder": "Dencho",
    "type": "Andrews 77",
    "designer": "Andrews",
    "year": 2003,
    "sizes": {
      "loa": 23.47,
      "beam": 4.73,
      "draft": 4.3,
      "displacement": 13490.0,
      "genoa": 102.8,
      "main": 147.15,
      "spinnaker": 0.0,
      "spinnaker_asym": 438.38,
      "crew": 1920.0,
      "wetted_surface": 72.83
    },
    "stability_index": -1.0
  },
  "vpp": {
    "angles": [
      52,
      60,
      75,
      90,
      110,
      120,
      135,
      150
    ],
    "speeds": [
      4,
      6,
      8,
      10,
      12,
      14,
      16,
      20,
      24
    ],
    "52": [
      6.24,
      8.76,
      10.08,
      10.63,
      10.99,
      11.27,
      11.49,
      11.81,
      11.86
    ],
    "60": [
      6.85,
      9.43,
      10.62,
      11.1,
      11.44,
      11.75,
      12.02,
      12.41,
      12.51
    ],
    "75": [
      7.51,
      10.04,
      11.2,
      11.73,
      12.13,
      12.53,
      12.88,
      13.41,
      13.71
    ],
    "90": [
      7.51,
      10.09,
      11.3,
      12.16,
      12.71,
      13.14,
      13.65,
      14.46,
      15.06
    ],
    "110": [
      6.43,
      9.08,
      10.72,
      11.71,
      12.66,
      13.66,
      14.47,
      15.8,
      17.01
    ],
    "120": [
      5.67,
      8.3,
      10.34,
      11.52,
      12.37,
      13.18,
      13.99,
      16.27,
      17.71
    ],
    "135": [
      5.03,
      7.51,
      9.71,
      11.21,
      12.48,
      13.74,
      14.85,
      16.95,
      18.83
    ],
    "150": [
      4.19,
      6.27,
      8.26,
      9.88,
      11.12,
      12.4,
      13.8,
      17.03,
      20.01
    ],
    "beat_angle": [
      47.1,
      45.1,
      41.2,
      39.8,
      39.1,
      38.4,
      38,
      37.3,
      37.6
    ],
    "beat_vmg": [
      3.93,
      5.62,
      6.72,
      7.23,
      7.59,
      7.86,
      8.06,
      8.3,
      8.3
    ],
    "run_angle": [
      139.9,
      140.6,
      141.1,
      145.3,
      147.6,
      147.1,
      147.6,
      150.5,
      153.7
    ],
    "run_vmg": [
      3.63,
      5.43,
      7.15,
      8.56,
      9.63,
      10.74,
      11.95,
      14.76,
      17.54
    ]
  }
}