{
  "sailnumber": "CAN/CAN94",
  "country": "CAN",
  "name": "Freestyle",
  "rating": {
    "gph": 579.1,
    "osn": 562.4,
    "triple_offshore": [
      0.9101,
      1.1688,
      1.2958
    ],
    "triple_inshore": [
      0.7065,
      0.9517,
      1.0764
    ]
  },
  "boat": {
    "builder": "J Boats USA/France",
    "type": "J 120",
    "designer": "Johnstone",
    "year": 1994,
    "sizes": {
      "loa": 12.244,
      "beam": 3.67,
      "draft": 2.19,
      "displacement": 7600.0,
      "genoa": 51.05,
      "main": 47.41,
      "spinnaker": 0.0,
      "spinnaker_asym": 148.41,
      "crew": 829.0,
      "wetted_surface": 34.1
    },
    "stability_index": -1.0
  },
  "vpp": {
    "angles": [
      52,
      60,
      75,
      90,
      110,
      120,
      135,
      150
    ],
    "speeds": [
      4,
      6,
      8,
      10,
      12,
      14,
      16,
      20,
      24
    ],
    "52": [
      4.28,
      5.76,
      6.8,
      7.37,
      7.61,
      7.73,
      7.8,
      7.89,
      7.93
    ],
    "60": [
      4.57,
      6.06,
      7.04,
      7.55,
      7.8,
      7.92,
      8.0,
      8.11,
      8.17
    ],
    "75": [
      4.76,
      6.25,
      7.18,
      7.68,
      7.98,
      8.17,
      8.29,
      8.49,
      8.61
    ],
    "90": [
      4.51,
      6.1,
      7.2,
      7.77,
      8.04,
      8.3,
      8.53,
      8.85,
      9.08
    ],
    "110": [
      4.47,
      6.13,
      7.34,
      7.97,
      8.37,
      8.66,
      8.93,
      9.4,
      9.79
    ],
    "120": [
      4.35,
      6.01,
      7.26,
      7.94,
      8.4,
      8.82,
      9.19,
      9.83,
      10.64
    ],
    "135": [
      3.72,
      5.33,
      6.69,
      7.6,
      8.13,
      8.62,
      9.11,
      10.22,
      12.14
    ],
    "150": [
      3.14,
      4.48,
      5.67,
      6.75,
      7.57,
      8.04,
      8.45,
      9.3,
      10.69
    ],
    "beat_angle": [
      43.1,
      43.1,
      41,
      39.5,
      38.3,
      37.6,
      37.1,
      36.7,
      37
    ],
    "beat_vmg": [
      2.73,
      3.78,
      4.6,
      5.14,
      5.39,
      5.53,
      5.62,
      5.73,
      5.73
    ],
    "run_angle": [
      142.6,
      142.6,
      146.7,
      147.5,
      152,
      155.1,
      159.3,
      158.6,
      141.3
    ],
    "run_vmg": [
      2.72,
      3.88,
      4.91,
      5.84,
      6.58,
      7.03,
      7.42,
      8.13,
      9.25
    ]
  }
}