{
  "sailnumber": "LAT/LAT717",
  "country": "LAT",
  "name": "Estelle",
  "rating": {
    "gph": 622.2,
    "osn": 603.1,
    "triple_offshore": [
      0.8456,
      1.0886,
      1.207
    ],
    "triple_inshore": [
      0.6582,
      0.8909,
      1.0145
    ]
  },
  "boat": {
    "builder": "BENETEAU",
    "type": "FIRST 35",
    "designer": "FARR",
    "year": 2009,
    "sizes": {
      "loa": 10.66,
      "beam": 3.64,
      "draft": 2.19,
      "displacement": 5536.0,
      "genoa": 32.06,
      "main": 41.54,
      "spinnaker": 94.8,
      "spinnaker_asym": 0.0,
      "crew": 705.0,
      "wetted_surface": 27.66
    },
    "stability_index": -1.0
  },
  "vpp": {
    "angles": [
      52,
      60,
      75,
      90,
      110,
      120,
      135,
      150
    ],
    "speeds": [
      4,
      6,
      8,
      10,
      12,
      14,
      16,
      20,
      24
    ],
    "52": [
      3.97,
      5.34,
      6.3,
      6.85,
      7.1,
      7.2,
      7.27,
      7.34,
      7.32
    ],
    "60": [
      4.23,
      5.62,
      6.53,
      7.04,
      7.29,
      7.4,
      7.48,
      7.56,
      7.54
    ],
    "75": [
      4.4,
      5.8,
      6.7,
      7.18,
      7.48,
      7.67,
      7.79,
      7.95,
      8.01
    ],
    "90": [
      4.24,
      5.68,
      6.68,
      7.22,
      7.52,
      7.79,
      8.02,
      8.32,
      8.49
    ],
    "110": [
      4.17,
      5.7,
      6.82,
      7.4,
      7.78,
      8.08,
      8.28,
      8.61,
      8.88
    ],
    "120": [
      4.01,
      5.52,
      6.66,
      7.32,
      7.76,
      8.15,
      8.5,
      9.02,
      9.43
    ],
    "135": [
      3.53,
      4.95,
      6.13,
      6.97,
      7.49,
      7.91,
      8.34,
      9.26,
      10.65
    ],
    "150": [
      2.89,
      4.17,
      5.33,
      6.32,
      7.05,
      7.52,
      7.91,
      8.74,
      9.84
    ],
    "beat_angle": [
      43.3,
      43.3,
      40.9,
      39.3,
      38.5,
      38.2,
      38,
      38.8,
      39.5
    ],
    "beat_vmg": [
      2.54,
      3.5,
      4.26,
      4.76,
      4.99,
      5.1,
      5.16,
      5.19,
      5.08
    ],
    "run_angle": [
      144.9,
      144.9,
      149.6,
      152.5,
      159.2,
      166.6,
      174.5,
      176.8,
      175.4
    ],
    "run_vmg": [
      2.51,
      3.62,
      4.62,
      5.49,
      6.24,
      6.84,
      7.3,
      8.04,
      8.8
    ]
  }
}