{
  "sailnumber": "ESP/ESP11342",
  "country": "ESP",
  "name": "IBEROLIMP ALHAMBRA DOS",
  "rating": {
    "gph": 670.2,
    "osn": 650.2,
    "triple_offshore": [
      0.7871,
      1.0097,
      1.1179
    ],
    "triple_inshore": [
      0.6134,
      0.822,
      0.9243
    ]
  },
  "boat": {
    "builder": "BENETEAU",
    "type": "FIRST CL.CHALLENGE",
    "designer": "FINOT",
    "year": 1990,
    "sizes": {
      "loa": 9.147,
      "beam": 3.23,
      "draft": 1.82,
      "displacement": 3011.0,
      "genoa": 25.37,
      "main": 25.68,
      "spinnaker": 63.22,
      "spinnaker_asym": 0.0,
      "crew": 320.0,
      "wetted_surface": 20.2
    },
    "stability_index": 95.2
  },
  "vpp": {
    "angles": [
      52,
      60,
      75,
      90,
      110,
      120,
      135,
      150
    ],
    "speeds": [
      4,
      6,
      8,
      10,
      12,
      14,
      16,
      20,
      24
    ],
    "52": [
      3.58,
      4.95,
      5.81,
      6.32,
      6.53,
      6.61,
      6.66,
      6.68,
      6.6
    ],
    "60": [
      3.85,
      5.21,
      6.05,
      6.52,
      6.75,
      6.84,
      6.9,
      6.94,
      6.9
    ],
    "75": [
      4.03,
      5.39,
      6.22,
      6.69,
      6.97,
      7.15,
      7.26,
      7.4,
      7.44
    ],
    "90": [
      3.9,
      5.3,
      6.19,
      6.71,
      7.04,
      7.33,
      7.56,
      7.86,
      8.03
    ],
    "110": [
      3.77,
      5.31,
      6.34,
      6.91,
      7.31,
      7.62,
      7.83,
      8.18,
      8.49
    ],
    "120": [
      3.63,
      5.14,
      6.22,
      6.86,
      7.31,
      7.75,
      8.14,
      8.73,
      9.24
    ],
    "135": [
      3.18,
      4.62,
      5.74,
      6.54,
      7.06,
      7.53,
      8.01,
      9.28,
      10.85
    ],
    "150": [
      2.64,
      3.92,
      5.03,
      5.96,
      6.64,
      7.11,
      7.55,
      8.59,
      10.12
    ],
    "beat_angle": [
      46.1,
      43.4,
      41.1,
      39.8,
      39.5,
      39.5,
      39.7,
      40.6,
      42.9
    ],
    "beat_vmg": [
      2.28,
      3.25,
      3.93,
      4.35,
      4.51,
      4.57,
      4.6,
      4.56,
      4.34
    ],
    "run_angle": [
      142.2,
      145.9,
      149.8,
      153.3,
      159.4,
      166.2,
      171.1,
      169.6,
      158.2
    ],
    "run_vmg": [
      2.29,
      3.39,
      4.35,
      5.18,
      5.87,
      6.44,
      6.88,
      7.7,
      8.82
    ]
  }
}