{
  "sailnumber": "ESP/ESP11349_C",
  "country": "ESP",
  "name": "VELALUKA",
  "rating": {
    "gph": 630.6,
    "osn": 613.1,
    "triple_offshore": [
      0.8388,
      1.071,
      1.1885
    ],
    "triple_inshore": [
      0.6524,
      0.8748,
      0.9937
    ]
  },
  "boat": {
    "builder": "DUFOUR",
    "type": "DUFOUR 34",
    "designer": "Felci Yachts",
    "year": 2002,
    "sizes": {
      "loa": 10.3,
      "beam": 3.48,
      "draft": 1.92,
      "displacement": 5148.0,
      "genoa": 37.93,
      "main": 35.4,
      "spinnaker": 79.81,
      "spinnaker_asym": 76.93,
      "crew": 300.0,
      "wetted_surface": 24.29
    },
    "stability_index": -1.0
  },
  "vpp": {
    "angles": [
      52,
      60,
      75,
      90,
      110,
      120,
      135,
      150
    ],
    "speeds": [
      4,
      6,
      8,
      10,
      12,
      14,
      16,
      20,
      24
    ],
    "52": [
      4.01,
      5.36,
      6.27,
      6.78,
      7.02,
      7.12,
      7.17,
      7.23,
      7.21
    ],
    "60": [
      4.27,
      5.63,
      6.49,
      6.96,
      7.19,
      7.31,
      7.37,
      7.47,
      7.47
    ],
    "75": [
      4.46,
      5.82,
      6.64,
      7.09,
      7.36,
      7.56,
      7.68,
      7.86,
      7.97
    ],
    "90": [
      4.35,
      5.72,
      6.6,
      7.14,
      7.46,
      7.67,
      7.9,
      8.22,
      8.45
    ],
    "110": [
      4.12,
      5.61,
      6.69,
      7.27,
      7.68,
      8.04,
      8.36,
      8.77,
      9.09
    ],
    "120": [
      3.98,
      5.45,
      6.54,
      7.17,
      7.6,
      8.0,
      8.4,
      9.2,
      9.8
    ],
    "135": [
      3.49,
      4.87,
      6.01,
      6.82,
      7.31,
      7.72,
      8.12,
      9.01,
      10.35
    ],
    "150": [
      2.87,
      4.1,
      5.21,
      6.15,
      6.86,
      7.32,
      7.71,
      8.5,
      9.51
    ],
    "beat_angle": [
      43,
      43,
      41.2,
      39.7,
      38.9,
      38.4,
      38.3,
      39.2,
      40.6
    ],
    "beat_vmg": [
      2.58,
      3.53,
      4.25,
      4.71,
      4.93,
      5.03,
      5.08,
      5.09,
      4.99
    ],
    "run_angle": [
      143.1,
      143.1,
      150.1,
      153.4,
      159.3,
      166.2,
      173.2,
      177.2,
      174.5
    ],
    "run_vmg": [
      2.48,
      3.55,
      4.51,
      5.35,
      6.06,
      6.65,
      7.1,
      7.83,
      8.57
    ]
  }
}