{
  "sailnumber": "USA/65376",
  "country": "USA",
  "name": "DISCOVER",
  "rating": {
    "gph": 614.9,
    "osn": 596.8,
    "triple_offshore": [
      0.8668,
      1.0948,
      1.2163
    ],
    "triple_inshore": [
      0.6779,
      0.9044,
      1.0234
    ]
  },
  "boat": {
    "builder": "TPI",
    "type": "J 33",
    "designer": "Johnstone",
    "year": 1988,
    "sizes": {
      "loa": 10.173,
      "beam": 3.31,
      "draft": 1.92,
      "displacement": 3444.0,
      "genoa": 38.69,
      "main": 31.79,
      "spinnaker": 76.41,
      "spinnaker_asym": 67.84,
      "crew": 680.0,
      "wetted_surface": 22.66
    },
    "stability_index": -1.0
  },
  "vpp": {
    "angles": [
      52,
      60,
      75,
      90,
      110,
      120,
      135,
      150
    ],
    "speeds": [
      4,
      6,
      8,
      10,
      12,
      14,
      16,
      20,
      24
    ],
    "52": [
      4.29,
      5.68,
      6.55,
      6.93,
      7.08,
      7.16,
      7.21,
      7.28,
      7.26
    ],
    "60": [
      4.59,
      5.95,
      6.71,
      7.06,
      7.24,
      7.34,
      7.4,
      7.5,
      7.51
    ],
    "75": [
      4.75,
      6.1,
      6.81,
      7.18,
      7.44,
      7.61,
      7.71,
      7.89,
      7.99
    ],
    "90": [
      4.58,
      5.96,
      6.76,
      7.23,
      7.55,
      7.79,
      8.01,
      8.3,
      8.55
    ],
    "110": [
      4.14,
      5.64,
      6.72,
      7.28,
      7.73,
      8.12,
      8.47,
      9.11,
      9.79
    ],
    "120": [
      3.98,
      5.47,
      6.56,
      7.17,
      7.64,
      8.11,
      8.58,
      9.72,
      11.07
    ],
    "135": [
      3.47,
      4.88,
      6.05,
      6.82,
      7.32,
      7.8,
      8.29,
      9.53,
      12.09
    ],
    "150": [
      2.87,
      4.13,
      5.28,
      6.24,
      6.9,
      7.36,
      7.8,
      8.77,
      10.45
    ],
    "beat_angle": [
      42.3,
      42.3,
      40.1,
      37.4,
      36.3,
      36,
      35.8,
      35.7,
      36.8
    ],
    "beat_vmg": [
      2.75,
      3.77,
      4.54,
      5.0,
      5.17,
      5.26,
      5.31,
      5.35,
      5.29
    ],
    "run_angle": [
      145.1,
      145.1,
      149.4,
      153.2,
      160.1,
      167.1,
      172.2,
      171.8,
      142.6
    ],
    "run_vmg": [
      2.48,
      3.58,
      4.57,
      5.42,
      6.12,
      6.68,
      7.12,
      7.93,
      9.05
    ]
  }
}