{
  "sailnumber": "USA/93213",
  "country": "USA",
  "name": "KAILANI",
  "rating": {
    "gph": 583.8,
    "osn": 568.5,
    "triple_offshore": [
      0.9092,
      1.1577,
      1.2694
    ],
    "triple_inshore": [
      0.7045,
      0.9395,
      1.0487
    ]
  },
  "boat": {
    "builder": "Fairport Yachts LTD",
    "type": "C&C 121",
    "designer": "",
    "year": 2002,
    "sizes": {
      "loa": 12.268,
      "beam": 4.01,
      "draft": 2.0,
      "displacement": 7766.0,
      "genoa": 51.65,
      "main": 47.36,
      "spinnaker": 0.0,
      "spinnaker_asym": 154.79,
      "crew": 785.0,
      "wetted_surface": 35.1
    },
    "stability_index": -1.0
  },
  "vpp": {
    "angles": [
      52,
      60,
      75,
      90,
      110,
      120,
      135,
      150
    ],
    "speeds": [
      4,
      6,
      8,
      10,
      12,
      14,
      16,
      20,
      24
    ],
    "52": [
      4.18,
      5.66,
      6.73,
      7.29,
      7.49,
      7.57,
      7.63,
      7.66,
      7.64
    ],
    "60": [
      4.48,
      5.98,
      6.98,
      7.5,
      7.7,
      7.78,
      7.84,
      7.9,
      7.91
    ],
    "75": [
      4.69,
      6.2,
      7.15,
      7.65,
      7.93,
      8.07,
      8.16,
      8.29,
      8.36
    ],
    "90": [
      4.65,
      6.23,
      7.29,
      7.78,
      7.99,
      8.26,
      8.46,
      8.69,
      8.84
    ],
    "110": [
      4.52,
      6.18,
      7.38,
      7.96,
      8.32,
      8.6,
      8.85,
      9.24,
      9.5
    ],
    "120": [
      4.41,
      6.06,
      7.29,
      7.94,
      8.4,
      8.78,
      9.1,
      9.69,
      10.22
    ],
    "135": [
      3.82,
      5.42,
      6.74,
      7.59,
      8.12,
      8.61,
      9.09,
      10.21,
      11.74
    ],
    "150": [
      3.21,
      4.56,
      5.75,
      6.8,
      7.56,
      8.02,
      8.42,
      9.27,
      10.64
    ],
    "beat_angle": [
      44,
      44,
      42,
      40.3,
      39.3,
      38.8,
      38.7,
      38.8,
      40.1
    ],
    "beat_vmg": [
      2.66,
      3.69,
      4.51,
      5.03,
      5.24,
      5.35,
      5.39,
      5.43,
      5.29
    ],
    "run_angle": [
      142.8,
      142.8,
      146.8,
      148.5,
      152.1,
      155.7,
      159.9,
      159.3,
      141.3
    ],
    "run_vmg": [
      2.78,
      3.95,
      4.98,
      5.89,
      6.57,
      7.02,
      7.41,
      8.11,
      9.22
    ]
  }
}