{
  "sailnumber": "USA/USA118",
  "country": "USA",
  "name": "THUNDERSTRUCK3",
  "rating": {
    "gph": 566.0,
    "osn": 553.4,
    "triple_offshore": [
      0.9625,
      1.1731,
      1.3227
    ],
    "triple_inshore": [
      0.757,
      0.9556,
      1.0996
    ]
  },
  "boat": {
    "builder": "Hansheng Yachts",
    "type": "Flying Tiger 10",
    "designer": "Robert H. Perry",
    "year": 2007,
    "sizes": {
      "loa": 9.94,
      "beam": 2.79,
      "draft": 2.27,
      "displacement": 2189.0,
      "genoa": 24.4,
      "main": 39.25,
      "spinnaker": 0.0,
      "spinnaker_asym": 101.36,
      "crew": 550.0,
      "wetted_surface": 19.42
    },
    "stability_index": -1.0
  },
  "vpp": {
    "angles": [
      52,
      60,
      75,
      90,
      110,
      120,
      135,
      150
    ],
    "speeds": [
      4,
      6,
      8,
      10,
      12,
      14,
      16,
      20,
      24
    ],
    "52": [
      4.49,
      6.08,
      6.86,
      7.12,
      7.26,
      7.35,
      7.43,
      7.47,
      7.37
    ],
    "60": [
      4.82,
      6.37,
      7.08,
      7.34,
      7.5,
      7.62,
      7.71,
      7.8,
      7.73
    ],
    "75": [
      5.06,
      6.57,
      7.26,
      7.66,
      7.89,
      8.06,
      8.21,
      8.37,
      8.42
    ],
    "90": [
      4.92,
      6.49,
      7.23,
      7.77,
      8.2,
      8.5,
      8.74,
      9.11,
      9.37
    ],
    "110": [
      4.75,
      6.53,
      7.43,
      7.93,
      8.35,
      8.75,
      9.14,
      10.13,
      10.86
    ],
    "120": [
      4.58,
      6.42,
      7.43,
      8.15,
      8.7,
      9.21,
      9.73,
      10.77,
      11.79
    ],
    "135": [
      4.1,
      5.84,
      7.06,
      7.84,
      8.69,
      9.67,
      10.7,
      12.29,
      13.88
    ],
    "150": [
      3.4,
      4.91,
      6.15,
      7.07,
      7.79,
      8.54,
      9.55,
      12.35,
      15.91
    ],
    "beat_angle": [
      44.9,
      41.9,
      39.2,
      37.7,
      37.4,
      37.2,
      37.1,
      37.8,
      39.9
    ],
    "beat_vmg": [
      2.89,
      4.05,
      4.75,
      5.03,
      5.17,
      5.26,
      5.32,
      5.29,
      5.1
    ],
    "run_angle": [
      139.6,
      142.2,
      146.4,
      152.3,
      152,
      149,
      145.9,
      146.8,
      150.4
    ],
    "run_vmg": [
      2.95,
      4.25,
      5.32,
      6.14,
      6.76,
      7.4,
      8.27,
      10.69,
      13.79
    ]
  }
}