{
  "sailnumber": "USA/USA25600",
  "country": "USA",
  "name": "RAMPAGE",
  "rating": {
    "gph": 518.6,
    "osn": 504.9,
    "triple_offshore": [
      1.0241,
      1.2979,
      1.4611
    ],
    "triple_inshore": [
      0.7917,
      1.0537,
      1.2126
    ]
  },
  "boat": {
    "builder": "Carroll",
    "type": "Concordia 47",
    "designer": "Farr",
    "year": 1999,
    "sizes": {
      "loa": 14.298,
      "beam": 4.18,
      "draft": 2.91,
      "displacement": 7878.0,
      "genoa": 51.19,
      "main": 77.15,
      "spinnaker": 165.11,
      "spinnaker_asym": 142.06,
      "crew": 1105.0,
      "wetted_surface": 39.01
    },
    "stability_index": -1.0
  },
  "vpp": {
    "angles": [
      52,
      60,
      75,
      90,
      110,
      120,
      135,
      150
    ],
    "speeds": [
      4,
      6,
      8,
      10,
      12,
      14,
      16,
      20,
      24
    ],
    "52": [
      5.0,
      6.67,
      7.75,
      8.18,
      8.38,
      8.52,
      8.62,
      8.76,
      8.77
    ],
    "60": [
      5.34,
      7.01,
      8.01,
      8.42,
      8.62,
      8.77,
      8.88,
      9.05,
      9.11
    ],
    "75": [
      5.61,
      7.26,
      8.19,
      8.65,
      8.94,
      9.14,
      9.31,
      9.56,
      9.71
    ],
    "90": [
      5.44,
      7.12,
      8.12,
      8.66,
      9.08,
      9.43,
      9.7,
      10.12,
      10.43
    ],
    "110": [
      5.02,
      6.84,
      8.14,
      8.84,
      9.4,
      9.84,
      10.21,
      10.87,
      11.39
    ],
    "120": [
      4.74,
      6.59,
      7.99,
      8.74,
      9.37,
      10.0,
      10.64,
      11.67,
      12.56
    ],
    "135": [
      4.11,
      5.83,
      7.28,
      8.26,
      8.91,
      9.56,
      10.29,
      12.07,
      14.48
    ],
    "150": [
      3.39,
      4.84,
      6.13,
      7.29,
      8.24,
      8.85,
      9.47,
      11.0,
      13.16
    ],
    "beat_angle": [
      42.6,
      42.6,
      39.9,
      38,
      37.1,
      36.9,
      36.5,
      36.2,
      37.1
    ],
    "beat_vmg": [
      3.19,
      4.41,
      5.31,
      5.76,
      5.99,
      6.14,
      6.24,
      6.36,
      6.3
    ],
    "run_angle": [
      141.1,
      141.1,
      143,
      146.2,
      154.4,
      162.4,
      166.4,
      159.9,
      148
    ],
    "run_vmg": [
      2.94,
      4.19,
      5.31,
      6.32,
      7.21,
      7.89,
      8.45,
      9.59,
      11.4
    ]
  }
}