{
  "sailnumber": "GER/GER7885",
  "country": "GER",
  "name": "MADAMEX2",
  "rating": {
    "gph": 583.3,
    "osn": 565.6,
    "triple_offshore": [
      0.9034,
      1.1596,
      1.2928
    ],
    "triple_inshore": [
      0.7034,
      0.949,
      1.0847
    ]
  },
  "boat": {
    "builder": "X-YACHTS",
    "type": "IMX-40 MODIF",
    "designer": "JEPPESEN",
    "year": 2000,
    "sizes": {
      "loa": 12.1,
      "beam": 3.78,
      "draft": 2.47,
      "displacement": 6710.0,
      "genoa": 45.44,
      "main": 49.11,
      "spinnaker": 106.91,
      "spinnaker_asym": 0.0,
      "crew": 600.0,
      "wetted_surface": 31.07
    },
    "stability_index": -1.0
  },
  "vpp": {
    "angles": [
      52,
      60,
      75,
      90,
      110,
      120,
      135,
      150
    ],
    "speeds": [
      4,
      6,
      8,
      10,
      12,
      14,
      16,
      20,
      24
    ],
    "52": [
      4.35,
      5.83,
      6.85,
      7.38,
      7.61,
      7.72,
      7.78,
      7.86,
      7.86
    ],
    "60": [
      4.62,
      6.12,
      7.07,
      7.56,
      7.8,
      7.92,
      8.0,
      8.09,
      8.12
    ],
    "75": [
      4.82,
      6.31,
      7.21,
      7.69,
      7.99,
      8.21,
      8.34,
      8.52,
      8.62
    ],
    "90": [
      4.68,
      6.18,
      7.14,
      7.68,
      8.03,
      8.34,
      8.6,
      8.96,
      9.2
    ],
    "110": [
      4.32,
      5.94,
      7.13,
      7.79,
      8.22,
      8.58,
      8.83,
      9.26,
      9.65
    ],
    "120": [
      4.18,
      5.76,
      6.97,
      7.69,
      8.18,
      8.64,
      9.07,
      9.75,
      10.35
    ],
    "135": [
      3.66,
      5.15,
      6.4,
      7.29,
      7.86,
      8.34,
      8.83,
      10.0,
      11.71
    ],
    "150": [
      3.0,
      4.33,
      5.54,
      6.57,
      7.35,
      7.88,
      8.33,
      9.31,
      10.69
    ],
    "beat_angle": [
      42.4,
      42.4,
      40.4,
      38.7,
      37.6,
      37.1,
      37.2,
      37.3,
      38.3
    ],
    "beat_vmg": [
      2.81,
      3.86,
      4.67,
      5.19,
      5.42,
      5.54,
      5.6,
      5.65,
      5.6
    ],
    "run_angle": [
      144.4,
      144.4,
      148.7,
      152.3,
      157.4,
      164.6,
      170,
      172.7,
      163.6
    ],
    "run_vmg": [
      2.6,
      3.75,
      4.79,
      5.7,
      6.47,
      7.11,
      7.61,
      8.45,
      9.39
    ]
  }
}