{
  "sailnumber": "ITA/ITA17548",
  "country": "ITA",
  "name": "ARIA",
  "rating": {
    "gph": 523.0,
    "osn": 507.7,
    "triple_offshore": [
      0.9998,
      1.2982,
      1.4477
    ],
    "triple_inshore": [
      0.7723,
      1.0477,
      1.1894
    ]
  },
  "boat": {
    "builder": "Cantiere del Pardo",
    "type": "Grand Soleil S 48 R",
    "designer": "Lostuzzi",
    "year": 2018,
    "sizes": {
      "loa": 14.95,
      "beam": 4.53,
      "draft": 3.02,
      "displacement": 12554.0,
      "genoa": 59.87,
      "main": 79.48,
      "spinnaker": 0.0,
      "spinnaker_asym": 218.38,
      "crew": 800.0,
      "wetted_surface": 49.04
    },
    "stability_index": 131.8
  },
  "vpp": {
    "angles": [
      52,
      60,
      75,
      90,
      110,
      120,
      135,
      150
    ],
    "speeds": [
      4,
      6,
      8,
      10,
      12,
      14,
      16,
      20,
      24
    ],
    "52": [
      4.52,
      6.19,
      7.45,
      8.18,
      8.47,
      8.62,
      8.72,
      8.83,
      8.84
    ],
    "60": [
      4.84,
      6.54,
      7.75,
      8.45,
      8.74,
      8.88,
      8.98,
      9.1,
      9.13
    ],
    "75": [
      5.09,
      6.8,
      7.95,
      8.62,
      8.99,
      9.21,
      9.36,
      9.57,
      9.67
    ],
    "90": [
      5.09,
      6.89,
      8.15,
      8.8,
      9.12,
      9.35,
      9.63,
      10.03,
      10.29
    ],
    "110": [
      4.92,
      6.78,
      8.18,
      8.95,
      9.4,
      9.77,
      10.16,
      10.78,
      11.23
    ],
    "120": [
      4.76,
      6.63,
      8.07,
      8.9,
      9.48,
      9.99,
      10.38,
      11.25,
      12.24
    ],
    "135": [
      4.16,
      5.94,
      7.45,
      8.45,
      9.09,
      9.66,
      10.27,
      11.8,
      13.39
    ],
    "150": [
      3.47,
      4.96,
      6.29,
      7.46,
      8.39,
      8.97,
      9.46,
      10.51,
      12.25
    ],
    "beat_angle": [
      43.4,
      43.4,
      41.5,
      39.7,
      38.5,
      38.1,
      37.9,
      38.2,
      39.3
    ],
    "beat_vmg": [
      2.88,
      4.05,
      5.0,
      5.62,
      5.91,
      6.06,
      6.16,
      6.27,
      6.19
    ],
    "run_angle": [
      141.5,
      141.5,
      144.9,
      147.3,
      151.8,
      154,
      157.4,
      154.6,
      142.2
    ],
    "run_vmg": [
      3.01,
      4.3,
      5.45,
      6.46,
      7.28,
      7.83,
      8.28,
      9.12,
      10.61
    ]
  }
}