{
  "sailnumber": "ITA/ITA43013",
  "country": "ITA",
  "name": "NEO KIKA",
  "rating": {
    "gph": 510.1,
    "osn": 496.5,
    "triple_offshore": [
      1.0336,
      1.3202,
      1.5128
    ],
    "triple_inshore": [
      0.7992,
      1.0615,
      1.2265
    ]
  },
  "boat": {
    "builder": "Neo Yachts & Composite",
    "type": "NEO 43 Roma",
    "designer": "Ceccarelli",
    "year": 2020,
    "sizes": {
      "loa": 13.074,
      "beam": 4.05,
      "draft": 2.9,
      "displacement": 6188.0,
      "genoa": 46.91,
      "main": 64.11,
      "spinnaker": 0.0,
      "spinnaker_asym": 166.46,
      "crew": 500.0,
      "wetted_surface": 36.52
    },
    "stability_index": 129.8
  },
  "vpp": {
    "angles": [
      52,
      60,
      75,
      90,
      110,
      120,
      135,
      150
    ],
    "speeds": [
      4,
      6,
      8,
      10,
      12,
      14,
      16,
      20,
      24
    ],
    "52": [
      4.64,
      6.45,
      7.62,
      8.17,
      8.46,
      8.62,
      8.74,
      8.89,
      8.92
    ],
    "60": [
      5.01,
      6.82,
      7.94,
      8.44,
      8.76,
      8.97,
      9.12,
      9.32,
      9.39
    ],
    "75": [
      5.31,
      7.11,
      8.15,
      8.72,
      9.14,
      9.51,
      9.75,
      10.1,
      10.28
    ],
    "90": [
      5.34,
      7.25,
      8.3,
      8.86,
      9.27,
      9.77,
      10.24,
      10.93,
      11.41
    ],
    "110": [
      5.16,
      7.11,
      8.29,
      9.05,
      9.76,
      10.44,
      11.03,
      11.99,
      12.6
    ],
    "120": [
      4.83,
      6.79,
      8.18,
      9.04,
      9.86,
      10.66,
      11.34,
      12.95,
      14.21
    ],
    "135": [
      4.25,
      6.15,
      7.66,
      8.57,
      9.38,
      10.29,
      11.4,
      13.69,
      15.67
    ],
    "150": [
      3.51,
      5.13,
      6.52,
      7.66,
      8.49,
      9.21,
      10.0,
      12.23,
      15.46
    ],
    "beat_angle": [
      45.6,
      43.2,
      41.1,
      39.3,
      38.2,
      38.2,
      37.9,
      37.8,
      38.9
    ],
    "beat_vmg": [
      2.96,
      4.23,
      5.12,
      5.66,
      5.93,
      6.08,
      6.17,
      6.27,
      6.19
    ],
    "run_angle": [
      138.9,
      141,
      144,
      148.9,
      152.9,
      151.2,
      148.6,
      145.1,
      145.8
    ],
    "run_vmg": [
      3.04,
      4.44,
      5.64,
      6.63,
      7.39,
      7.98,
      8.66,
      10.59,
      13.39
    ]
  }
}