{
  "sailnumber": "ITA/ITANND25",
  "country": "ITA",
  "name": "BUENAONDA",
  "rating": {
    "gph": 642.5,
    "osn": 623.6,
    "triple_offshore": [
      0.8177,
      1.0539,
      1.1751
    ],
    "triple_inshore": [
      0.6332,
      0.8558,
      0.9741
    ]
  },
  "boat": {
    "builder": "Elan Marine",
    "type": "Elan 340",
    "designer": "Humpreys",
    "year": 2006,
    "sizes": {
      "loa": 9.98,
      "beam": 3.47,
      "draft": 2.06,
      "displacement": 4999.0,
      "genoa": 23.74,
      "main": 32.99,
      "spinnaker": 0.0,
      "spinnaker_asym": 82.68,
      "crew": 375.0,
      "wetted_surface": 24.12
    },
    "stability_index": -1.0
  },
  "vpp": {
    "angles": [
      52,
      60,
      75,
      90,
      110,
      120,
      135,
      150
    ],
    "speeds": [
      4,
      6,
      8,
      10,
      12,
      14,
      16,
      20,
      24
    ],
    "52": [
      3.68,
      4.97,
      5.9,
      6.51,
      6.85,
      7.02,
      7.11,
      7.19,
      7.18
    ],
    "60": [
      3.91,
      5.23,
      6.15,
      6.7,
      7.01,
      7.19,
      7.31,
      7.41,
      7.43
    ],
    "75": [
      4.02,
      5.42,
      6.38,
      6.87,
      7.16,
      7.39,
      7.56,
      7.77,
      7.88
    ],
    "90": [
      4.3,
      5.74,
      6.69,
      7.16,
      7.43,
      7.6,
      7.74,
      8.05,
      8.3
    ],
    "110": [
      4.19,
      5.68,
      6.74,
      7.27,
      7.66,
      8.0,
      8.29,
      8.73,
      9.11
    ],
    "120": [
      4.05,
      5.53,
      6.61,
      7.19,
      7.59,
      7.98,
      8.37,
      9.13,
      9.9
    ],
    "135": [
      3.55,
      4.96,
      6.09,
      6.86,
      7.32,
      7.72,
      8.12,
      9.03,
      10.56
    ],
    "150": [
      2.93,
      4.18,
      5.28,
      6.19,
      6.84,
      7.25,
      7.59,
      8.28,
      9.11
    ],
    "beat_angle": [
      43.2,
      43.2,
      41,
      39.7,
      38.6,
      37.9,
      37.5,
      37.7,
      38.6
    ],
    "beat_vmg": [
      2.36,
      3.27,
      3.98,
      4.5,
      4.83,
      5.01,
      5.08,
      5.13,
      5.06
    ],
    "run_angle": [
      143.3,
      143.3,
      147.6,
      149.6,
      152.5,
      158.3,
      162.8,
      163.7,
      161
    ],
    "run_vmg": [
      2.54,
      3.62,
      4.57,
      5.36,
      5.95,
      6.39,
      6.77,
      7.38,
      7.98
    ]
  }
}