{
  "sailnumber": "NED/NED1524",
  "country": "NED",
  "name": "STELLA17",
  "rating": {
    "gph": 542.9,
    "osn": 527.1,
    "triple_offshore": [
      0.9655,
      1.2486,
      1.3984
    ],
    "triple_inshore": [
      0.7457,
      1.0117,
      1.1682
    ]
  },
  "boat": {
    "builder": "BASHFORD",
    "type": "SYDNEY 46",
    "designer": "MURRAY IAN",
    "year": 1997,
    "sizes": {
      "loa": 14.28,
      "beam": 4.05,
      "draft": 3.02,
      "displacement": 8964.0,
      "genoa": 49.66,
      "main": 71.06,
      "spinnaker": 138.62,
      "spinnaker_asym": 0.0,
      "crew": 940.0,
      "wetted_surface": 40.34
    },
    "stability_index": -1.0
  },
  "vpp": {
    "angles": [
      52,
      60,
      75,
      90,
      110,
      120,
      135,
      150
    ],
    "speeds": [
      4,
      6,
      8,
      10,
      12,
      14,
      16,
      20,
      24
    ],
    "52": [
      4.52,
      6.26,
      7.42,
      7.97,
      8.19,
      8.33,
      8.42,
      8.53,
      8.53
    ],
    "60": [
      4.86,
      6.59,
      7.69,
      8.22,
      8.43,
      8.56,
      8.66,
      8.78,
      8.82
    ],
    "75": [
      5.11,
      6.83,
      7.87,
      8.41,
      8.71,
      8.89,
      9.02,
      9.23,
      9.32
    ],
    "90": [
      4.96,
      6.69,
      7.79,
      8.4,
      8.8,
      9.11,
      9.36,
      9.69,
      9.91
    ],
    "110": [
      4.49,
      6.37,
      7.72,
      8.48,
      8.94,
      9.24,
      9.5,
      9.97,
      10.62
    ],
    "120": [
      4.3,
      6.16,
      7.55,
      8.37,
      8.92,
      9.41,
      9.84,
      10.5,
      11.13
    ],
    "135": [
      3.72,
      5.44,
      6.84,
      7.89,
      8.56,
      9.09,
      9.65,
      11.03,
      12.68
    ],
    "150": [
      3.07,
      4.54,
      5.81,
      6.96,
      7.9,
      8.53,
      9.04,
      10.2,
      11.86
    ],
    "beat_angle": [
      45.2,
      42.7,
      40.5,
      38.7,
      37.8,
      37.4,
      37.5,
      37.2,
      38.2
    ],
    "beat_vmg": [
      2.89,
      4.13,
      5.03,
      5.55,
      5.78,
      5.93,
      6.02,
      6.13,
      6.06
    ],
    "run_angle": [
      139.1,
      141.2,
      146,
      149.4,
      154.7,
      161.4,
      168,
      169.6,
      156.8
    ],
    "run_vmg": [
      2.66,
      3.93,
      5.03,
      6.03,
      6.9,
      7.6,
      8.19,
      9.14,
      10.31
    ]
  }
}