{
  "sailnumber": "NED/NED8075",
  "country": "NED",
  "name": "Zeehond",
  "rating": {
    "gph": 578.6,
    "osn": 562.1,
    "triple_offshore": [
      0.8975,
      1.1752,
      1.3183
    ],
    "triple_inshore": [
      0.6883,
      0.9425,
      1.0873
    ]
  },
  "boat": {
    "builder": "X-Yachts",
    "type": "XC-45",
    "designer": "N. Jeppesen",
    "year": 2009,
    "sizes": {
      "loa": 13.634,
      "beam": 4.31,
      "draft": 2.21,
      "displacement": 13673.0,
      "genoa": 55.41,
      "main": 61.79,
      "spinnaker": 0.0,
      "spinnaker_asym": 135.98,
      "crew": 928.0,
      "wetted_surface": 44.38
    },
    "stability_index": -1.0
  },
  "vpp": {
    "angles": [
      52,
      60,
      75,
      90,
      110,
      120,
      135,
      150
    ],
    "speeds": [
      4,
      6,
      8,
      10,
      12,
      14,
      16,
      20,
      24
    ],
    "52": [
      4.01,
      5.59,
      6.66,
      7.4,
      7.82,
      8.04,
      8.14,
      8.24,
      8.26
    ],
    "60": [
      4.37,
      5.93,
      6.97,
      7.65,
      8.04,
      8.26,
      8.38,
      8.48,
      8.52
    ],
    "75": [
      4.65,
      6.18,
      7.22,
      7.85,
      8.22,
      8.47,
      8.65,
      8.85,
      8.95
    ],
    "90": [
      4.74,
      6.4,
      7.52,
      8.14,
      8.47,
      8.68,
      8.82,
      9.13,
      9.39
    ],
    "110": [
      4.59,
      6.25,
      7.43,
      8.13,
      8.57,
      8.92,
      9.24,
      9.71,
      10.11
    ],
    "120": [
      4.29,
      5.95,
      7.19,
      8.01,
      8.49,
      8.87,
      9.24,
      9.97,
      10.5
    ],
    "135": [
      3.67,
      5.29,
      6.54,
      7.52,
      8.15,
      8.58,
      8.96,
      9.76,
      10.63
    ],
    "150": [
      3.02,
      4.44,
      5.63,
      6.64,
      7.48,
      8.05,
      8.44,
      9.1,
      9.8
    ],
    "beat_angle": [
      47.7,
      44.5,
      42.4,
      41,
      40.2,
      39.5,
      39.1,
      38.9,
      39.4
    ],
    "beat_vmg": [
      2.52,
      3.61,
      4.42,
      5.02,
      5.41,
      5.6,
      5.71,
      5.79,
      5.76
    ],
    "run_angle": [
      138.5,
      142.3,
      146.9,
      149,
      150.6,
      154,
      159.7,
      177.9,
      178.4
    ],
    "run_vmg": [
      2.62,
      3.84,
      4.87,
      5.75,
      6.48,
      7.02,
      7.48,
      8.2,
      8.81
    ]
  }
}