{
  "sailnumber": "FRA/FRA6374",
  "country": "FRA",
  "name": "ELMA RLEQUIN",
  "rating": {
    "gph": 722.8,
    "osn": 699.4,
    "triple_offshore": [
      0.7316,
      0.9347,
      1.0357
    ],
    "triple_inshore": [
      0.575,
      0.7727,
      0.8755
    ]
  },
  "boat": {
    "builder": "QUERE",
    "type": "SUPER ARLEQUIN GTE",
    "designer": "MAURIC Andr\u00e9",
    "year": 1973,
    "sizes": {
      "loa": 9.21,
      "beam": 2.92,
      "draft": 1.69,
      "displacement": 2858.0,
      "genoa": 24.98,
      "main": 16.42,
      "spinnaker": 52.68,
      "spinnaker_asym": 0.0,
      "crew": 384.0,
      "wetted_surface": 15.78
    },
    "stability_index": -1.0
  },
  "vpp": {
    "angles": [
      52,
      60,
      75,
      90,
      110,
      120,
      135,
      150
    ],
    "speeds": [
      4,
      6,
      8,
      10,
      12,
      14,
      16,
      20,
      24
    ],
    "52": [
      3.41,
      4.62,
      5.41,
      5.83,
      6.06,
      6.19,
      6.24,
      6.28,
      6.27
    ],
    "60": [
      3.64,
      4.84,
      5.6,
      5.98,
      6.2,
      6.33,
      6.41,
      6.47,
      6.49
    ],
    "75": [
      3.79,
      4.96,
      5.72,
      6.11,
      6.34,
      6.51,
      6.64,
      6.83,
      6.92
    ],
    "90": [
      3.66,
      4.86,
      5.66,
      6.15,
      6.4,
      6.58,
      6.78,
      7.13,
      7.33
    ],
    "110": [
      3.51,
      4.86,
      5.79,
      6.28,
      6.59,
      6.88,
      7.16,
      7.47,
      7.67
    ],
    "120": [
      3.38,
      4.71,
      5.67,
      6.22,
      6.57,
      6.9,
      7.24,
      7.73,
      8.01
    ],
    "135": [
      2.99,
      4.29,
      5.26,
      5.98,
      6.39,
      6.72,
      7.08,
      7.76,
      8.34
    ],
    "150": [
      2.5,
      3.69,
      4.68,
      5.5,
      6.08,
      6.43,
      6.74,
      7.42,
      8.05
    ],
    "beat_angle": [
      45.8,
      42.9,
      41,
      39.3,
      38,
      37.7,
      37.8,
      38.2,
      39.3
    ],
    "beat_vmg": [
      2.18,
      3.06,
      3.67,
      4.09,
      4.33,
      4.42,
      4.48,
      4.48,
      4.41
    ],
    "run_angle": [
      143.8,
      147.9,
      151.8,
      154.6,
      162.6,
      168.7,
      176.8,
      177,
      177.2
    ],
    "run_vmg": [
      2.16,
      3.19,
      4.06,
      4.8,
      5.44,
      5.91,
      6.28,
      6.85,
      7.47
    ]
  }
}