{
  "sailnumber": "GRE/GRE1432",
  "country": "GRE",
  "name": "IPSIPILI",
  "rating": {
    "gph": 636.2,
    "osn": 612.7,
    "triple_offshore": [
      0.7981,
      1.078,
      1.2256
    ],
    "triple_inshore": [
      0.6155,
      0.8722,
      1.0304
    ]
  },
  "boat": {
    "builder": "ELAN",
    "type": "ELAN 40 SD FK",
    "designer": "HUMPHREYS",
    "year": 2002,
    "sizes": {
      "loa": 11.913,
      "beam": 3.84,
      "draft": 2.06,
      "displacement": 8098.0,
      "genoa": 36.81,
      "main": 45.79,
      "spinnaker": 99.48,
      "spinnaker_asym": 0.0,
      "crew": 750.0,
      "wetted_surface": 32.93
    },
    "stability_index": -1.0
  },
  "vpp": {
    "angles": [
      52,
      60,
      75,
      90,
      110,
      120,
      135,
      150
    ],
    "speeds": [
      4,
      6,
      8,
      10,
      12,
      14,
      16,
      20,
      24
    ],
    "52": [
      3.47,
      4.97,
      6.02,
      6.75,
      7.18,
      7.4,
      7.51,
      7.6,
      7.62
    ],
    "60": [
      3.77,
      5.29,
      6.32,
      7.0,
      7.38,
      7.59,
      7.71,
      7.82,
      7.86
    ],
    "75": [
      3.98,
      5.49,
      6.53,
      7.18,
      7.54,
      7.78,
      7.95,
      8.16,
      8.26
    ],
    "90": [
      3.85,
      5.37,
      6.53,
      7.27,
      7.64,
      7.84,
      8.07,
      8.44,
      8.7
    ],
    "110": [
      3.8,
      5.43,
      6.66,
      7.41,
      7.82,
      8.14,
      8.41,
      8.78,
      9.07
    ],
    "120": [
      3.65,
      5.24,
      6.46,
      7.29,
      7.77,
      8.12,
      8.46,
      9.12,
      9.56
    ],
    "135": [
      3.17,
      4.67,
      5.88,
      6.85,
      7.49,
      7.9,
      8.26,
      9.05,
      9.94
    ],
    "150": [
      2.63,
      3.93,
      5.1,
      6.12,
      6.96,
      7.52,
      7.9,
      8.61,
      9.43
    ],
    "beat_angle": [
      47.3,
      44.9,
      42.6,
      41.1,
      39.9,
      39,
      38.5,
      38.2,
      38.8
    ],
    "beat_vmg": [
      2.19,
      3.2,
      3.98,
      4.57,
      4.98,
      5.21,
      5.32,
      5.4,
      5.37
    ],
    "run_angle": [
      142.4,
      145.3,
      149.2,
      151.6,
      156.3,
      163.2,
      170,
      178.1,
      177.2
    ],
    "run_vmg": [
      2.27,
      3.41,
      4.42,
      5.3,
      6.1,
      6.75,
      7.27,
      8.0,
      8.66
    ]
  }
}