{
  "sailnumber": "ITA/ITA16478",
  "country": "ITA",
  "name": "ZEN 2",
  "rating": {
    "gph": 579.0,
    "osn": 559.4,
    "triple_offshore": [
      0.8887,
      1.1786,
      1.3291
    ],
    "triple_inshore": [
      0.6879,
      0.9549,
      1.1136
    ]
  },
  "boat": {
    "builder": "Beneteau",
    "type": "First 45",
    "designer": "Briand",
    "year": 2008,
    "sizes": {
      "loa": 13.665,
      "beam": 4.2,
      "draft": 2.78,
      "displacement": 11766.0,
      "genoa": 51.98,
      "main": 57.64,
      "spinnaker": 135.88,
      "spinnaker_asym": 0.0,
      "crew": 510.0,
      "wetted_surface": 42.24
    },
    "stability_index": 123.1
  },
  "vpp": {
    "angles": [
      52,
      60,
      75,
      90,
      110,
      120,
      135,
      150
    ],
    "speeds": [
      4,
      6,
      8,
      10,
      12,
      14,
      16,
      20,
      24
    ],
    "52": [
      4.02,
      5.6,
      6.71,
      7.45,
      7.85,
      8.04,
      8.13,
      8.23,
      8.25
    ],
    "60": [
      4.33,
      5.92,
      7.0,
      7.7,
      8.07,
      8.26,
      8.36,
      8.47,
      8.51
    ],
    "75": [
      4.58,
      6.15,
      7.21,
      7.86,
      8.25,
      8.5,
      8.67,
      8.85,
      8.95
    ],
    "90": [
      4.44,
      6.02,
      7.12,
      7.87,
      8.25,
      8.56,
      8.81,
      9.19,
      9.42
    ],
    "110": [
      4.22,
      5.96,
      7.26,
      8.06,
      8.51,
      8.86,
      9.07,
      9.43,
      9.61
    ],
    "120": [
      4.07,
      5.79,
      7.07,
      7.94,
      8.45,
      8.86,
      9.23,
      9.81,
      10.23
    ],
    "135": [
      3.53,
      5.16,
      6.44,
      7.44,
      8.12,
      8.58,
      9.0,
      9.89,
      11.0
    ],
    "150": [
      2.91,
      4.32,
      5.56,
      6.63,
      7.51,
      8.13,
      8.57,
      9.39,
      10.37
    ],
    "beat_angle": [
      46.5,
      43.4,
      41.1,
      40,
      38.8,
      38.2,
      37.9,
      37.8,
      38.3
    ],
    "beat_vmg": [
      2.55,
      3.67,
      4.51,
      5.12,
      5.49,
      5.66,
      5.76,
      5.84,
      5.82
    ],
    "run_angle": [
      137.6,
      144.2,
      148.2,
      151.6,
      155.3,
      161.7,
      167.3,
      176.8,
      174.5
    ],
    "run_vmg": [
      2.52,
      3.74,
      4.81,
      5.75,
      6.56,
      7.25,
      7.82,
      8.65,
      9.41
    ]
  }
}