{
  "sailnumber": "ESP/ESP8931_C",
  "country": "ESP",
  "name": "ALCOR TRES",
  "rating": {
    "gph": 650.0,
    "osn": 633.1,
    "triple_offshore": [
      0.8204,
      1.0362,
      1.1413
    ],
    "triple_inshore": [
      0.6391,
      0.8451,
      0.9486
    ]
  },
  "boat": {
    "builder": "MOA",
    "type": "RO 340",
    "designer": "RONAUTICA",
    "year": 2005,
    "sizes": {
      "loa": 9.585,
      "beam": 3.26,
      "draft": 2.0,
      "displacement": 4603.0,
      "genoa": 33.3,
      "main": 32.48,
      "spinnaker": 0.0,
      "spinnaker_asym": 66.79,
      "crew": 300.0,
      "wetted_surface": 22.35
    },
    "stability_index": -1.0
  },
  "vpp": {
    "angles": [
      52,
      60,
      75,
      90,
      110,
      120,
      135,
      150
    ],
    "speeds": [
      4,
      6,
      8,
      10,
      12,
      14,
      16,
      20,
      24
    ],
    "52": [
      3.89,
      5.24,
      6.1,
      6.56,
      6.78,
      6.87,
      6.93,
      6.98,
      6.97
    ],
    "60": [
      4.17,
      5.5,
      6.31,
      6.73,
      6.94,
      7.05,
      7.11,
      7.18,
      7.19
    ],
    "75": [
      4.39,
      5.68,
      6.45,
      6.85,
      7.09,
      7.26,
      7.38,
      7.53,
      7.62
    ],
    "90": [
      4.28,
      5.6,
      6.43,
      6.92,
      7.22,
      7.38,
      7.57,
      7.87,
      8.09
    ],
    "110": [
      3.98,
      5.5,
      6.51,
      7.03,
      7.39,
      7.72,
      8.03,
      8.45,
      8.77
    ],
    "120": [
      3.83,
      5.34,
      6.38,
      6.95,
      7.33,
      7.69,
      8.06,
      8.82,
      9.32
    ],
    "135": [
      3.33,
      4.77,
      5.87,
      6.63,
      7.08,
      7.44,
      7.81,
      8.66,
      9.69
    ],
    "150": [
      2.75,
      4.02,
      5.09,
      5.98,
      6.62,
      7.01,
      7.32,
      7.98,
      8.76
    ],
    "beat_angle": [
      46.3,
      42.7,
      40.7,
      39.3,
      38.3,
      37.8,
      37.7,
      38.5,
      39.7
    ],
    "beat_vmg": [
      2.48,
      3.47,
      4.15,
      4.59,
      4.81,
      4.9,
      4.95,
      4.96,
      4.88
    ],
    "run_angle": [
      139,
      143.4,
      147.8,
      149.6,
      153,
      159.4,
      163.9,
      175.7,
      174.8
    ],
    "run_vmg": [
      2.38,
      3.48,
      4.41,
      5.18,
      5.76,
      6.21,
      6.59,
      7.23,
      7.81
    ]
  }
}