{
  "sailnumber": "ESP/IRL8164_C",
  "country": "ESP",
  "name": "ENIGMA",
  "rating": {
    "gph": 704.1,
    "osn": 683.7,
    "triple_offshore": [
      0.7676,
      0.9484,
      1.0529
    ],
    "triple_inshore": [
      0.609,
      0.7912,
      0.8843
    ]
  },
  "boat": {
    "builder": "",
    "type": "QUARTER TON",
    "designer": "ED DUBOIS",
    "year": 1977,
    "sizes": {
      "loa": 7.57,
      "beam": 2.68,
      "draft": 1.56,
      "displacement": 1339.0,
      "genoa": 15.79,
      "main": 18.76,
      "spinnaker": 42.31,
      "spinnaker_asym": 0.0,
      "crew": 355.0,
      "wetted_surface": 11.2
    },
    "stability_index": -1.0
  },
  "vpp": {
    "angles": [
      52,
      60,
      75,
      90,
      110,
      120,
      135,
      150
    ],
    "speeds": [
      4,
      6,
      8,
      10,
      12,
      14,
      16,
      20,
      24
    ],
    "52": [
      3.72,
      4.88,
      5.52,
      5.85,
      6.04,
      6.16,
      6.22,
      6.28,
      6.26
    ],
    "60": [
      3.94,
      5.07,
      5.65,
      5.96,
      6.17,
      6.33,
      6.43,
      6.54,
      6.54
    ],
    "75": [
      4.1,
      5.18,
      5.74,
      6.06,
      6.32,
      6.56,
      6.76,
      6.96,
      7.05
    ],
    "90": [
      4.0,
      5.12,
      5.82,
      6.2,
      6.48,
      6.69,
      6.95,
      7.34,
      7.59
    ],
    "110": [
      3.85,
      5.15,
      5.87,
      6.31,
      6.74,
      7.09,
      7.38,
      7.78,
      8.04
    ],
    "120": [
      3.72,
      5.01,
      5.76,
      6.22,
      6.68,
      7.08,
      7.47,
      8.31,
      9.05
    ],
    "135": [
      3.28,
      4.56,
      5.44,
      5.97,
      6.39,
      6.84,
      7.25,
      8.29,
      10.22
    ],
    "150": [
      2.73,
      3.92,
      4.9,
      5.6,
      6.05,
      6.45,
      6.87,
      7.69,
      9.06
    ],
    "beat_angle": [
      44.9,
      41.8,
      39.7,
      37.3,
      36.3,
      36.2,
      36.3,
      37.1,
      39.1
    ],
    "beat_vmg": [
      2.4,
      3.27,
      3.86,
      4.22,
      4.42,
      4.49,
      4.52,
      4.51,
      4.38
    ],
    "run_angle": [
      140.4,
      147.5,
      152.4,
      159.2,
      166.4,
      175.4,
      176.3,
      176.8,
      145.9
    ],
    "run_vmg": [
      2.37,
      3.4,
      4.25,
      4.95,
      5.5,
      5.93,
      6.29,
      7.03,
      7.85
    ]
  }
}