{
  "sailnumber": "USA/USA31074",
  "country": "USA",
  "name": "WARRIOR WON",
  "rating": {
    "gph": 552.2,
    "osn": 535.4,
    "triple_offshore": [
      0.9454,
      1.2207,
      1.4292
    ],
    "triple_inshore": [
      0.7371,
      0.9778,
      1.1587
    ]
  },
  "boat": {
    "builder": "Cape Performance",
    "type": "Cape 31",
    "designer": "Mark Mills",
    "year": 2016,
    "sizes": {
      "loa": 9.573,
      "beam": 3.05,
      "draft": 2.44,
      "displacement": 1847.0,
      "genoa": 24.44,
      "main": 37.96,
      "spinnaker": 0.0,
      "spinnaker_asym": 116.12,
      "crew": 675.0,
      "wetted_surface": 20.88
    },
    "stability_index": 108.7
  },
  "vpp": {
    "angles": [
      52,
      60,
      75,
      90,
      110,
      120,
      135,
      150
    ],
    "speeds": [
      4,
      6,
      8,
      10,
      12,
      14,
      16,
      20,
      24
    ],
    "52": [
      4.22,
      5.89,
      6.9,
      7.41,
      7.64,
      7.81,
      7.94,
      8.13,
      8.13
    ],
    "60": [
      4.52,
      6.2,
      7.12,
      7.69,
      8.01,
      8.22,
      8.39,
      8.61,
      8.67
    ],
    "75": [
      4.74,
      6.42,
      7.27,
      7.96,
      8.54,
      8.87,
      9.14,
      9.51,
      9.72
    ],
    "90": [
      4.59,
      6.27,
      7.25,
      7.91,
      8.68,
      9.41,
      9.88,
      10.59,
      11.08
    ],
    "110": [
      4.59,
      6.5,
      7.62,
      8.48,
      9.08,
      9.66,
      10.21,
      11.59,
      12.88
    ],
    "120": [
      4.43,
      6.39,
      7.57,
      8.61,
      9.53,
      10.23,
      10.91,
      12.2,
      13.52
    ],
    "135": [
      3.94,
      5.68,
      7.09,
      8.05,
      9.14,
      10.4,
      11.76,
      13.82,
      15.8
    ],
    "150": [
      3.25,
      4.75,
      6.02,
      7.05,
      7.98,
      8.92,
      10.07,
      13.37,
      17.02
    ],
    "beat_angle": [
      45,
      42.7,
      40.4,
      38.7,
      37.8,
      37.6,
      37.4,
      37.4,
      38.2
    ],
    "beat_vmg": [
      2.7,
      3.88,
      4.72,
      5.18,
      5.37,
      5.47,
      5.54,
      5.63,
      5.57
    ],
    "run_angle": [
      139.2,
      141.9,
      145.3,
      148.9,
      150.3,
      146,
      145.4,
      144.4,
      149
    ],
    "run_vmg": [
      2.82,
      4.12,
      5.22,
      6.11,
      6.91,
      7.73,
      8.72,
      11.58,
      14.74
    ]
  }
}